{
  "hash": "2d8e25c6",
  "configHash": "f7a16535",
  "lockfileHash": "41b0158b",
  "browserHash": "caa557bd",
  "optimized": {
    "react": {
      "src": "../../node_modules/react/index.js",
      "file": "react.js",
      "fileHash": "fc7a4780",
      "needsInterop": true
    },
    "react-dom/client": {
      "src": "../../node_modules/react-dom/client.js",
      "file": "react-dom_client.js",
      "fileHash": "359128d6",
      "needsInterop": true
    },
    "axios": {
      "src": "../../node_modules/axios/index.js",
      "file": "axios.js",
      "fileHash": "d1d037c2",
      "needsInterop": false
    },
    "@mui/material": {
      "src": "../../node_modules/@mui/material/index.js",
      "file": "@mui_material.js",
      "fileHash": "c45d6934",
      "needsInterop": false
    }
  },
  "chunks": {
    "chunk-UP6LQVYV": {
      "file": "chunk-UP6LQVYV.js"
    },
    "chunk-TWJRYSII": {
      "file": "chunk-TWJRYSII.js"
    },
    "chunk-DC5AMYBS": {
      "file": "chunk-DC5AMYBS.js"
    }
  }
}